src/Comparator/comparator.v
module comparator
#(
    parameter nb = 2 // Parameter - # of bits
)
(
    input wire [nb-1:0] A,
    input wire [nb-1:0] B,
    output wire G,
    output wire E,
    output wire L
);

    // Assign
    // assign G = A > B;
    assign G = A[1] & ~B[1] | A[1] & A[0] & ~B[0] | A[0] & ~B[1] & ~B[0];
    // assign E = A == B;
    assign E = ~A[1] & ~A[0] & ~B[1] & ~B[0] |
               ~A[1] & A[0] & ~B[1] & B[0] |
               A[1] & ~A[0] & B[1] & ~B[0] |
               A[1] & A[0] & B[1] & B[0];
    // assign L = A < B;
    assign L = ~A[1] & B[1] | ~A[1] & ~A[0] & B[0] | ~A[0] & B[1] & B[0];

endmodule

src/Comparator/comparator_tb.v
`timescale 1ns / 1 ns
`include "comparator.v"

module comparator_tb;

    reg [1:0] A;
    reg [1:0] B;
    wire G;
    wire E;
    wire L;

    comparator uut (
        A,
        B,
        G,
        E,
        L
    );

    initial begin
        $dumpfile("comparator_tb.vcd");
        $dumpvars(0, comparator_tb);

        {A, B} = 4'd0; #20;
        {A, B} = 4'd1; #20;
        {A, B} = 4'd2; #20;
        {A, B} = 4'd3; #20;
        {A, B} = 4'd4; #20;
        {A, B} = 4'd5; #20;
        {A, B} = 4'd6; #20;
        {A, B} = 4'd7; #20;
        {A, B} = 4'd8; #20;
        {A, B} = 4'd9; #20;
        {A, B} = 4'd10; #20;
        {A, B} = 4'd11; #20;
        {A, B} = 4'd12; #20;
        {A, B} = 4'd13; #20;
        {A, B} = 4'd14; #20;
        {A, B} = 4'd15; #20;

        $display("Testbench Completed");
    end

endmodule

src/Comparator/comparator_tb.vcd
$date
	Tue Oct 15 09:36:21 2024
$end
$version
	Icarus Verilog
$end
$timescale
	1ns
$end
$scope module comparator_tb $end
$var wire 1 ! L $end
$var wire 1 " G $end
$var wire 1 # E $end
$var reg 2 $ A [1:0] $end
$var reg 2 % B [1:0] $end
$scope module uut $end
$var wire 2 & A [1:0] $end
$var wire 2 ' B [1:0] $end
$var wire 1 # E $end
$var wire 1 " G $end
$var wire 1 ! L $end
$var parameter 32 ( nb $end
$upscope $end
$upscope $end
$enddefinitions $end
$comment Show the parameter values. $end
$dumpall
b10 (
$end
#0
$dumpvars
b0 '
b0 &
b0 %
b0 $
1#
0"
0!
$end
#20
0#
1!
b1 %
b1 '
#40
0#
b10 %
b10 '
#60
b11 %
b11 '
#80
0#
1"
0!
b1 $
b1 &
b0 %
b0 '
#100
1#
0"
b1 %
b1 '
#120
0#
0"
1!
b10 %
b10 '
#140
b11 %
b11 '
#160
1"
0!
b10 $
b10 &
b0 %
b0 '
#180
b1 %
b1 '
#200
0"
1#
b10 %
b10 '
#220
0#
1!
b11 %
b11 '
#240
1"
0!
b11 $
b11 &
b0 %
b0 '
#260
b1 %
b1 '
#280
b10 %
b10 '
#300
0"
1#
b11 %
b11 '
